tdutils/__init__.py
tdutils/_arguments.py
tdutils/agolutil.py
tdutils/argutil.py
tdutils/cctvutil.py
tdutils/datautil.py
tdutils/emailutil.py
tdutils/external.py
tdutils/fulcutil.py
tdutils/jobutil.py
tdutils/kitsutil.py
tdutils/knackutil.py
tdutils/logutil.py
tdutils/pgrestutil.py
tdutils/socratautil.py
tdutils-0.0.15.dist-info/METADATA
tdutils-0.0.15.dist-info/RECORD
tdutils-0.0.15.dist-info/WHEEL
tdutils-0.0.15.dist-info/top_level.txt
