Metadata-Version: 2.1
Name: tdutils
Version: 0.0.15
Summary: Various utilities for managing and pulishing transportation data.
Home-page: https://github.com/cityofaustin/transportation-data-utils
Author: City of Austin
Author-email: transportation.data@austintexas.gov
License: UNKNOWN
Platform: UNKNOWN
Classifier: Programming Language :: Python :: 3
Classifier: License :: Public Domain
Classifier: Operating System :: OS Independent
Classifier: Development Status :: 4 - Beta
Requires-Dist: arrow
Requires-Dist: requests
Requires-Dist: arcgis
Requires-Dist: pymssql
Requires-Dist: yagmail
